src/__init__.py
src/kangaroo.py
tests/__init__.py
tests/kangaroo_test.py
kangaroo_sockets-0.1.dist-info/LICENSE
kangaroo_sockets-0.1.dist-info/METADATA
kangaroo_sockets-0.1.dist-info/WHEEL
kangaroo_sockets-0.1.dist-info/top_level.txt
kangaroo_sockets-0.1.dist-info/RECORD
