Metadata-Version: 2.1
Name: kangaroo-sockets
Version: 0.1
Summary: User-friendly lib for sockets in Python
Home-page: https://github.com/leozz37/kangaroo
Author: Leonardo Lima
Author-email: leonardoaugusto287@gmail.com
License: UNKNOWN
Platform: UNKNOWN
Classifier: Programming Language :: Python :: 3
Classifier: License :: OSI Approved :: MIT License
Classifier: Operating System :: OS Independent
Requires-Python: >=3.6
